omjlcomps/__init__.py
omjlcomps/juliapkg.json
omjlcomps/test/__init__.py
omjlcomps/test/test_aviary_support.py
omjlcomps/test/test_ecomp.jl
omjlcomps/test/test_explicit_ad_shape_by_conn.py
omjlcomps/test/test_icomp.jl
omjlcomps/test/test_julia_explicit_comp.py
omjlcomps/test/test_julia_implicit_comp.py
omjlcomps-0.2.6.dist-info/licenses/LICENSE
omjlcomps-0.2.6.dist-info/METADATA
omjlcomps-0.2.6.dist-info/WHEEL
omjlcomps-0.2.6.dist-info/entry_points.txt
omjlcomps-0.2.6.dist-info/top_level.txt
omjlcomps-0.2.6.dist-info/RECORD
