Metadata-Version: 2.4
Name: omjlcomps
Version: 0.2.6
Summary: Create OpenMDAO Components using the Julia programming language
License: MIT
Keywords: openmdao_component
License-File: LICENSE
Requires-Dist: openmdao~=3.36
Requires-Dist: juliapkg~=0.1.10
Requires-Dist: juliacall~=0.9.13
Provides-Extra: test
Requires-Dist: om-aviary; extra == "test"
Dynamic: license-file
